textlocal_pro-0.2.9.dist-info/METADATA
textlocal_pro-0.2.9.dist-info/RECORD
textlocal_pro-0.2.9.dist-info/WHEEL
textlocal_pro-0.2.9.dist-info/top_level.txt
textlocal_python/__init__.py
textlocal_python/http_client.py
textlocal_python/textlocal_python.py
