Metadata-Version: 2.1
Name: textlocal-pro
Version: 0.2.9
Summary: TextLocal REST API Implementation in Python
Home-page: https://github.com/the-procedure/textlocal_python
Author: Makarand Deshpande
Author-email: makarand_deshpande@outlook.com
License: MIT license
Keywords: textlocal-pro
Platform: UNKNOWN
Classifier: Development Status :: 4 - Beta
Classifier: Intended Audience :: Developers
Classifier: License :: OSI Approved :: MIT License
Classifier: Natural Language :: English
Classifier: Programming Language :: Python :: 3.4
Classifier: Programming Language :: Python :: 3.5
Classifier: Programming Language :: Python :: 3.6
